<?xml version="1.0" encoding="utf-16"?><SpaPackageImportExportData xmlns:xsd="http://www.w3.org/2001/XMLSchema" xmlns:xsi="http://www.w3.org/2001/XMLSchema-instance" dbversion="7.10"><PackageSummary><SpaPackageIdentity><Id>192EDDD960DF4DE0A0710A0F8828EA07</Id><Name>onePackage</Name><Version>7</Version></SpaPackageIdentity><Description /><CategoryIdentity><Id>201F370CA5164F76ADDD8EEEFF666AF7</Id><AutomaticallyPopulate>true</AutomaticallyPopulate><Name>Default Category</Name></CategoryIdentity><LastModifiedDateTime>2021-05-07T18:39:56.487</LastModifiedDateTime><LastModifiedResource><Id>6CA0D65FC8464F7A96DFF35D0C45AF57</Id><AutomaticallyPopulate>true</AutomaticallyPopulate><Name>phani.sastry</Name><ResourceType>Worker</ResourceType><EmailAddress /><UserId /><ManagerialLevel>0</ManagerialLevel></LastModifiedResource><Comments /><ResourceAccessTokens><ResourceAccess><ResourceIdentity><Id>7DF43CCDF24611D2804B00104B71BD15</Id><AutomaticallyPopulate>true</AutomaticallyPopulate><Name>Everyone</Name><ResourceType>GroupOfWorkers</ResourceType><EmailAddress /><UserId /><ManagerialLevel>0</ManagerialLevel></ResourceIdentity><AccessType>MaintenanceAccess</AccessType><PermissionType>FullControl</PermissionType></ResourceAccess></ResourceAccessTokens><PermissionType>FullControl</PermissionType><SourceControlStatus>ItemNotInSourceControl</SourceControlStatus></PackageSummary><Processes><ImportExportPackageSummaryOfProcessIdentity><Identity><Id>D77A797245602FD71E6BCABAECDF1671</Id><AutomaticallyPopulate>true</AutomaticallyPopulate><Version>2</Version><Name>1process</Name></Identity><LastModifiedBy><Id>6CA0D65FC8464F7A96DFF35D0C45AF57</Id><AutomaticallyPopulate>true</AutomaticallyPopulate><ResourceType>Worker</ResourceType><EmailAddress /><UserId /><ManagerialLevel>0</ManagerialLevel></LastModifiedBy><LastModified>2021-05-07T18:38:19.973</LastModified></ImportExportPackageSummaryOfProcessIdentity></Processes><ProcessExportOption><ExportResources>false</ExportResources><ExportGroupResourceMembers>false</ExportGroupResourceMembers><ExportResourcesExtensions>false</ExportResourcesExtensions><ExportCategories>false</ExportCategories><WithCategoryParentage>false</WithCategoryParentage><GeneralizedExport>false</GeneralizedExport><ExportDotNetReferencesWithPath>true</ExportDotNetReferencesWithPath><ExportCaseFragments>false</ExportCaseFragments><ExportTemplateSkins>false</ExportTemplateSkins><ExportExtractionClassificationData>true</ExportExtractionClassificationData><ExportGlobalDataModels>false</ExportGlobalDataModels><ExportProcessDataModels>false</ExportProcessDataModels><ExportType>CombineAssociatedMaps</ExportType><Version>0</Version><ExportServerVariables>true</ExportServerVariables><PreloadScript>1</PreloadScript><SleepDuration>0</SleepDuration><CategoryIds /><ProcessDocument>false</ProcessDocument><ProcessViewer>false</ProcessViewer><DotNetActivityType>0</DotNetActivityType><Projects /><AllProcessVariables /><ExportOnlyDocumentGroupIdentityDetails>false</ExportOnlyDocumentGroupIdentityDetails><SiteDetailsRequired>false</SiteDetailsRequired><CmisSiteDetailsRequired>false</CmisSiteDetailsRequired><Assets /><PerceptiveSiteDetailsRequired>false</PerceptiveSiteDetailsRequired><IncludeExportConnectorMappings>false</IncludeExportConnectorMappings><IsSpaExport>false</IsSpaExport><ProcessType>BusinessProcess</ProcessType><ProtectedItems /><ExportPageRenditions>false</ExportPageRenditions><ExportReportingTags>false</ExportReportingTags><IncludeProcessAssociationsInPackage>false</IncludeProcessAssociationsInPackage></ProcessExportOption><WorkAllocationRules /><Skins /><BusinessRules /><CustomServices /><CustomServiceGroups /><Assets /><Forms /><FormExportOptions><ExportHeader>false</ExportHeader><ExportNavigation>false</ExportNavigation><ExportGlobalVariables>true</ExportGlobalVariables><ExportWebServices>false</ExportWebServices><ExportBusinessRules>false</ExportBusinessRules><ExportSecurityTokens>false</ExportSecurityTokens><ExportSecurityRoles>false</ExportSecurityRoles><ExportRoleMembers>false</ExportRoleMembers><IsSpaExport>false</IsSpaExport></FormExportOptions><Navigations /><DeviceSettings /><Sites /><Themes /><Languages /><Lookups /><Resources /><Entities /><WorkTypes /><Checklists /><Folders /><ExtractionGroups /><ClassificationGroups /><Formatters /><FieldValidators /><ChecklistItems /><Events /><Targets /><Alerts /><AlertExportOption><ExportAssociatedProcess>false</ExportAssociatedProcess></AlertExportOption><Categories><ImportExportPackageSummaryOfCategoryIdentity><Identity><Id>201F370CA5164F76ADDD8EEEFF666AF7</Id><AutomaticallyPopulate>true</AutomaticallyPopulate><Name>Default Category</Name></Identity><LastModifiedBy><Id>7DF43CCDF24611D2804B00104B71BD10</Id><AutomaticallyPopulate>true</AutomaticallyPopulate><ResourceType>Worker</ResourceType><EmailAddress /><UserId /><ManagerialLevel>0</ManagerialLevel></LastModifiedBy><LastModified>2021-02-18T13:55:00</LastModified></ImportExportPackageSummaryOfCategoryIdentity></Categories><ScanVrsProfiles /><SeparationProfiles /><PdfGenerationProfiles /><DocConversionProfiles /><JobSchedules /><CaptureControlLayouts /><RegularExpressions /><Personas /><ServerVariables /><ServerVariablesCollection><ImportExportPackageSummaryOfVariable><Identity><VariableType>String</VariableType><Value xsi:type="xsd:string">phani</Value><Identity><Id>MYSERVERVAR</Id><Version>0</Version><DisplayName>myserverVar</DisplayName></Identity><Dynamic>false</Dynamic><Category><Id>201F370CA5164F76ADDD8EEEFF666AF7</Id><AutomaticallyPopulate>true</AutomaticallyPopulate><Name /></Category><Grouping><Identity><Id>4FEE4E069417475DAC5D2C2E5C95CA49</Id></Identity><Variables /></Grouping><UseInSkin>false</UseInSkin><Found>false</Found><IsSecure>false</IsSecure><VariableScope>Process</VariableScope><IsDateExpression>false</IsDateExpression><VariableDisplayProperties><VariableIdentity><Version>0</Version></VariableIdentity><StringVariableDisplayProperties><VariableControlType>Singleline</VariableControlType><MaxNumberOfCharacters>0</MaxNumberOfCharacters><LookupIdentity /><StaticData /><Mandatory>false</Mandatory></StringVariableDisplayProperties><MinDate xsi:nil="true" /><MaxDate xsi:nil="true" /><DecimalPrecision>0</DecimalPrecision></VariableDisplayProperties></Identity><LastModifiedBy><Id /><AutomaticallyPopulate>true</AutomaticallyPopulate><ResourceType>Worker</ResourceType><EmailAddress /><UserId /><ManagerialLevel>0</ManagerialLevel></LastModifiedBy><LastModified>0001-01-01T00:00:00</LastModified></ImportExportPackageSummaryOfVariable></ServerVariablesCollection><ThreadPools><ImportExportPackageSummaryOfThreadPoolIdentity><Identity><Id>0</Id><Name>Default Thread Pool</Name></Identity><LastModifiedBy><Id /><AutomaticallyPopulate>true</AutomaticallyPopulate><ResourceType>Worker</ResourceType><EmailAddress /><UserId /><ManagerialLevel>0</ManagerialLevel></LastModifiedBy><LastModified>0001-01-01T00:00:00</LastModified></ImportExportPackageSummaryOfThreadPoolIdentity></ThreadPools><Tags /><GlobalVariables /><GlobalVariablesCollection /><ServerXmlExpressionVariables /><DotNetReferences /><MiscellaneousFiles /><Queries /><FormTemplates /><Localisations /><Packages /><ExportConnectorDeploymentProperties /><ShowProcessAssociations>true</ShowProcessAssociations><ShowFormAssociations>true</ShowFormAssociations><SystemExportOptions><IncludeNoteTypes>false</IncludeNoteTypes><IncludeHotKeys>false</IncludeHotKeys><IncludePageRenditions>false</IncludePageRenditions><IncludeNodeColors>false</IncludeNodeColors><IncludeReportingTags>false</IncludeReportingTags></SystemExportOptions><ShowCategoryAssociations>false</ShowCategoryAssociations><Version><Major>7</Major><Minor>3</Minor><Build>1</Build><Revision>0</Revision></Version><DocumentTypeVariants /><ProtectAllItems>false</ProtectAllItems><ProtectedItems /><IncludeRoleMembers>false</IncludeRoleMembers><IncludeDevices>false</IncludeDevices><IncludeDeviceProfiles>false</IncludeDeviceProfiles><IncludeDeviceSettings>false</IncludeDeviceSettings><ExportConnectorMappings>false</ExportConnectorMappings><WebServices /><ImportConnections /><ImportSources /><OAuthServers /><CaptureSolution><Id /><Name /><Version>0</Version><Description /><DocumentLanguage /><CategoryIdentity><Id /><AutomaticallyPopulate>true</AutomaticallyPopulate><Name /></CategoryIdentity><LastModified>2021-05-13T19:25:52.4033674+05:30</LastModified><LockedBy><Id /><AutomaticallyPopulate>true</AutomaticallyPopulate><Name /><ResourceType>Worker</ResourceType><EmailAddress /><UserId /><ManagerialLevel>0</ManagerialLevel></LockedBy><ProcessIdentity><Id /><AutomaticallyPopulate>true</AutomaticallyPopulate><Version>0</Version><Name /></ProcessIdentity><ClassificationGroupIdentity><Id /><AutomaticallyPopulate>true</AutomaticallyPopulate><Version>0</Version><Name /></ClassificationGroupIdentity><GenerateMFPForms>false</GenerateMFPForms><ScanCNJFormLink /><ExpectedSolutionDuration>0</ExpectedSolutionDuration><UploadedDocsFolderId /><DownloadImagesAndData>false</DownloadImagesAndData><DeleteDocumentsWhenJobComplete>false</DeleteDocumentsWhenJobComplete><TrainingRequired>false</TrainingRequired><DownloadZipResources /><SeparationProfileIdentity /></CaptureSolution><DataModels /><QuickApp><Id /><Name /><Version>0</Version></QuickApp></SpaPackageImportExportData>